CHANGES.rst
CONTRIBUTORS.rst
LICENSE
MANIFEST.in
README.rst
requirements.txt
setup.py
tidehunter/__init__.py
tidehunter/stream.py
tidehunter.egg-info/PKG-INFO
tidehunter.egg-info/SOURCES.txt
tidehunter.egg-info/dependency_links.txt
tidehunter.egg-info/not-zip-safe
tidehunter.egg-info/requires.txt
tidehunter.egg-info/top_level.txt