Metadata-Version: 1.1
Name: tidehunter
Version: 1.0.1
Summary: HTTP streaming with accurate flow control
Home-page: https://github.com/woozyking/tidehunter
Author: Runzhou Li (Leo)
Author-email: runzhou.li@gmail.com
License: Copyright (c) 2014 Runzhou Li
